pep440_version_utils/__init__.py
pep440_version_utils/utils.py
pep440_version_utils/version.py
pep440_version_utils-1.1.0.dist-info/LICENSE
pep440_version_utils-1.1.0.dist-info/METADATA
pep440_version_utils-1.1.0.dist-info/WHEEL
pep440_version_utils-1.1.0.dist-info/RECORD
