Metadata-Version: 2.1
Name: pep440-version-utils
Version: 1.1.0
Summary: Utilities to deal with pep440 versioning
Home-page: https://github.com/m-vdb/pep440-version-utils
License: MIT
Keywords: pep440,version
Author: Maxime Verger
Author-email: me@maxvdb.com
Maintainer: Maxime Verger
Maintainer-email: me@maxvdb.com
Requires-Python: >=3.8,<3.13
Classifier: Development Status :: 4 - Beta
Classifier: Intended Audience :: Developers
Classifier: License :: OSI Approved :: MIT License
Classifier: Programming Language :: Python :: 3
Classifier: Programming Language :: Python :: 3.8
Classifier: Programming Language :: Python :: 3.9
Classifier: Programming Language :: Python :: 3.10
Classifier: Programming Language :: Python :: 3.11
Classifier: Programming Language :: Python :: 3.12
Requires-Dist: packaging (>=21.3,<24)
Project-URL: Repository, https://github.com/m-vdb/pep440-version-utils
